{
	"$schema" : "http://json-schema.org/draft-04/schema#",
	"title" : "rejectLeaveRes",
	"description" : "Reject leave json",
	"type" : "object",
	"properties" : {
		"cmd":{
			"type":"string",
			"minLength":3
		},
		"responseStatus":{
			"type":"string"
		},
		"errorCode":{
			"type":"string"
		},
		"errorMessage":{
			"type":"string"
		},
		"validationErrors":{
			"type":"array",
			"items":{
				"type":"object",
				"properties":{
					"code":{
						"type":"string"
					},
					"desc":{
						"type":"string"
					}
				}
			}
		},
	},
	"required" : ["cmd", "responseStatus"]

}